igwn_robot_auth/__init__.py
igwn_robot_auth/__main__.py
igwn_robot_auth/_version.py
igwn_robot_auth/htcondor.py
igwn_robot_auth/tests/__init__.py
igwn_robot_auth/tests/test_htcondor.py
igwn_robot_auth/tests/test_tools_get.py
igwn_robot_auth/tools/__init__.py
igwn_robot_auth/tools/core.py
igwn_robot_auth/tools/get.py
igwn_robot_auth-0.3.2.dist-info/licenses/LICENSE
igwn_robot_auth-0.3.2.dist-info/METADATA
igwn_robot_auth-0.3.2.dist-info/WHEEL
igwn_robot_auth-0.3.2.dist-info/entry_points.txt
igwn_robot_auth-0.3.2.dist-info/top_level.txt
igwn_robot_auth-0.3.2.dist-info/RECORD
