Metadata-Version: 2.4
Name: igwn-robot-auth
Version: 0.3.2
Summary: Auth credential management for IGWN robots
Author-email: Duncan Macleod <duncan.macleod@ligo.org>
License: MIT
Project-URL: Homepage, https://git.ligo.org/computing/software/igwn-robot-auth/
Project-URL: Documentation, https://rtd.igwn.org/projects/igwn-robot-auth/
Project-URL: Issues, https://git.ligo.org/computing/software/igwn-robot-auth/-/issues/
Project-URL: Source Code, https://git.ligo.org/computing/software/igwn-robot-auth.git
Classifier: Development Status :: 3 - Alpha
Classifier: Intended Audience :: Developers
Classifier: Intended Audience :: End Users/Desktop
Classifier: Intended Audience :: Science/Research
Classifier: Natural Language :: English
Classifier: Operating System :: Unix
Classifier: Programming Language :: Python
Classifier: Programming Language :: Python :: 3
Classifier: Programming Language :: Python :: 3.9
Classifier: Programming Language :: Python :: 3.10
Classifier: Programming Language :: Python :: 3.11
Classifier: Programming Language :: Python :: 3.12
Classifier: Programming Language :: Python :: 3.13
Classifier: Topic :: Scientific/Engineering
Classifier: Topic :: Scientific/Engineering :: Astronomy
Classifier: Topic :: Scientific/Engineering :: Physics
Requires-Python: >=3.9
License-File: LICENSE
Requires-Dist: igwn-auth-utils[gettoken,kerberos]>=1.3.0
Provides-Extra: docs
Requires-Dist: furo; extra == "docs"
Requires-Dist: myst-parser>=4.0.1; extra == "docs"
Requires-Dist: Sphinx>=7.1.0; extra == "docs"
Requires-Dist: sphinx-argparse; extra == "docs"
Requires-Dist: sphinx-automodapi; extra == "docs"
Requires-Dist: sphinx-copybutton; extra == "docs"
Requires-Dist: sphinx-design; extra == "docs"
Requires-Dist: sphinx-github-style; extra == "docs"
Requires-Dist: sphinx-substitution-extensions; extra == "docs"
Provides-Extra: htcondor
Requires-Dist: htcondor; extra == "htcondor"
Provides-Extra: test
Requires-Dist: pytest>=3.9.3; extra == "test"
Requires-Dist: pytest-cov; extra == "test"
Dynamic: license-file
